README.md
setup.py
pyunitgen/__init__.py
pyunitgen/cli.py
pyunitgen.egg-info/PKG-INFO
pyunitgen.egg-info/SOURCES.txt
pyunitgen.egg-info/dependency_links.txt
pyunitgen.egg-info/requires.txt
pyunitgen.egg-info/top_level.txt
pyunitgen/application/__init__.py
pyunitgen/application/unittestgenerator.py
pyunitgen/application/objects/__init__.py
pyunitgen/application/objects/generateunittests.py
pyunitgen/application/objects/generator.py
pyunitgen/application/objects/generatorunit.py
pyunitgen/application/objects/nodeparser.py
pyunitgen/application/objects/nodetype.py
pyunitgen/application/objects/pyunitexception.py
pyunitgen/application/objects/pyunitfile.py
pyunitgen/application/objects/pyunitreport.py
pyunitgen/application/objects/pyunittype.py
pyunitgen/application/objects/templates.py
sample/__init__.py
sample/animal.py
sample/file.py
sample/func.py
sample/person.py
sample/pet.py
sample/pet_main.py
sample/test.py
test/__init__.py
test/test_animal.py
test/test_file.py
test/test_func.py
test/test_person.py
test/test_pet.py
test/test_pet_main.py
test/test_test.py