Metadata-Version: 1.2
Name: pyunitgen
Version: 0.0.1a3
Summary: A python unittest generator for all your python files.
Home-page: https://github.com/eirtscience/pyunitgen
Author: Fangnikoue Evarist
Author-email: malevae@gmail.com
License: UNKNOWN
Platform: UNKNOWN
Classifier: Programming Language :: Python :: 3
Classifier: License :: OSI Approved :: GNU Affero General Public License v3
Classifier: Operating System :: OS Independent
Requires-Python: >=3.5
